nicegui_add/__init__.py
nicegui_add/aui/__init__.py
nicegui_add/aui/bar.py
nicegui_add/aui/breadcrumbs.py
nicegui_add/aui/button_group.py
nicegui_add/aui/carousel.py
nicegui_add/aui/intersection.py
nicegui_add/aui/space.py
nicegui_add/aui/toolbar.py
nicegui_add/aui/window_drag.py
nicegui_add/tests/__init__.py
nicegui_add/tests/bar.py
nicegui_add/tests/breadcrumbs.py
nicegui_add/tests/carousel.py
nicegui_add/tests/frameless_window.py
nicegui_add/tests/intersection.py
nicegui_add/tests/toolbar.py
nicegui_add-0.0.4.dist-info/METADATA
nicegui_add-0.0.4.dist-info/WHEEL
nicegui_add-0.0.4.dist-info/RECORD
