Metadata-Version: 2.1
Name: nicegui-add
Version: 0.0.4
Summary: nicegui补充组件
Home-page: https://gitlab.com/XiangQinxi/nicegui-add
Keywords: nicegui,web
Author: XiangQinxi
Author-email: XiangQinxi@outlook.com
Requires-Python: >=3.9,<4.0
Classifier: Programming Language :: Python :: 3
Classifier: Programming Language :: Python :: 3.9
Classifier: Programming Language :: Python :: 3.10
Classifier: Programming Language :: Python :: 3.11
Provides-Extra: all
Requires-Dist: darkdetect (>=0.8.0,<0.9.0) ; extra == "all"
Requires-Dist: nicegui (>=1.4.0,<2.0.0)
Project-URL: Documentation, https://nicegui-add.netlify.app
Project-URL: Repository, https://gitlab.com/XiangQinxi/nicegui-add
